local_port_scanner/__init__.py
local_port_scanner/netdiscover.py
local_port_scanner/port_scanner.py
local_port_scanner-0.0.2.dist-info/LICENSE
local_port_scanner-0.0.2.dist-info/METADATA
local_port_scanner-0.0.2.dist-info/WHEEL
local_port_scanner-0.0.2.dist-info/top_level.txt
local_port_scanner-0.0.2.dist-info/RECORD
