Metadata-Version: 2.1
Name: local-port-scanner
Version: 0.0.2
Summary: Simple local port scanner
Home-page: https://github.com/Osadhi/Local-Port-Scanner
Author: Osadhi Virochana
Author-email: virochana.osadhi@gmail.com
License: UNKNOWN
Platform: UNKNOWN
Classifier: Programming Language :: Python :: 3
Classifier: License :: OSI Approved :: MIT License
Classifier: Operating System :: OS Independent
Requires-Python: >=3.5
